ddlpy/__init__.py
ddlpy/cli.py
ddlpy/ddlpy.py
ddlpy/endpoints.json
ddlpy/utils.py
ddlpy/waterinfo.py
rws_ddlpy-0.10.0.dist-info/licenses/LICENSE
rws_ddlpy-0.10.0.dist-info/METADATA
rws_ddlpy-0.10.0.dist-info/WHEEL
rws_ddlpy-0.10.0.dist-info/entry_points.txt
rws_ddlpy-0.10.0.dist-info/top_level.txt
rws_ddlpy-0.10.0.dist-info/RECORD
