Metadata-Version: 2.4
Name: rws-ddlpy
Version: 0.10.0
Summary: Service from Rijkswaterstaat for distributing water quantity data.
Maintainer-email: Fedor Baart <fedor.baart@deltares.nl>, Jelmer Veenstra <jelmer.veenstra@deltares.nl>
License-Expression: GPL-3.0
Project-URL: Home, https://github.com/deltares/ddlpy
Project-URL: Code, https://github.com/deltares/ddlpy
Project-URL: Issues, https://github.com/deltares/ddlpy/issues
Keywords: ddlpy
Classifier: Development Status :: 3 - Alpha
Classifier: Intended Audience :: Developers
Classifier: Intended Audience :: Science/Research
Classifier: Operating System :: OS Independent
Classifier: Natural Language :: English
Classifier: Programming Language :: Python
Classifier: Programming Language :: Python :: 3
Classifier: Programming Language :: Python :: 3.9
Classifier: Programming Language :: Python :: 3.10
Classifier: Programming Language :: Python :: 3.11
Classifier: Programming Language :: Python :: 3.12
Classifier: Programming Language :: Python :: 3.13
Classifier: Programming Language :: Python :: 3.14
Requires-Python: >=3.9
License-File: LICENSE
Requires-Dist: numpy>=1.22
Requires-Dist: pandas
Requires-Dist: python-dateutil>=2.8
Requires-Dist: pytz
Requires-Dist: tqdm
Requires-Dist: click
Requires-Dist: requests
Requires-Dist: platformdirs
Provides-Extra: dev
Requires-Dist: bump2version>=0.5.11; extra == "dev"
Requires-Dist: flake8; extra == "dev"
Requires-Dist: pytest>=3.8.2; extra == "dev"
Requires-Dist: pytest-cov; extra == "dev"
Requires-Dist: twine; extra == "dev"
Requires-Dist: build; extra == "dev"
Requires-Dist: flake8>=3.5.0; extra == "dev"
Requires-Dist: tox>=3.5.2; extra == "dev"
Requires-Dist: twine>=1.12.1; extra == "dev"
Provides-Extra: docs
Requires-Dist: sphinx>=1.8.1; extra == "docs"
Requires-Dist: sphinx_mdinclude; extra == "docs"
Requires-Dist: nbsphinx; extra == "docs"
Requires-Dist: pydata-sphinx-theme; extra == "docs"
Provides-Extra: examples
Requires-Dist: jupyter; extra == "examples"
Requires-Dist: notebook; extra == "examples"
Requires-Dist: matplotlib; extra == "examples"
Provides-Extra: netcdf
Requires-Dist: xarray; extra == "netcdf"
Requires-Dist: h5netcdf; extra == "netcdf"
Dynamic: license-file
